tests/__init__.py
texion/__init__.py
texion/datasets/__init__.py
texion/datasets/datasets.py
texion/embeddings/__init__.py
texion/embeddings/word2vec.py
texion/encoders/__init__.py
texion/metrics/__init__.py
texion/models/__init__.py
texion/models/core.py
texion/models/sklearn/__init__.py
texion/models/sklearn/base_sklearn.py
texion/models/torch/__init__.py
texion/models/torch/base_torch.py
texion/models/torch/yoonkim.py
texion/utils/__init__.py
texion/utils/general.py
texion/utils/preprocess.py
texion-0.1.0.dist-info/METADATA
texion-0.1.0.dist-info/RECORD
texion-0.1.0.dist-info/WHEEL
texion-0.1.0.dist-info/top_level.txt
